mensaje_max1989-1.0.1.dist-info/licenses/LICENSE.txt
mensajes/__init__.py
mensajes/prueba.py
mensajes/adios/__init__.py
mensajes/adios/despedidas.py
mensajes/hola/Saludar.py
mensajes/hola/__init__.py
mensaje_max1989-1.0.1.dist-info/METADATA
mensaje_max1989-1.0.1.dist-info/WHEEL
mensaje_max1989-1.0.1.dist-info/top_level.txt
mensaje_max1989-1.0.1.dist-info/RECORD
