Metadata-Version: 2.4
Name: mensaje-max1989
Version: 1.0.1
Summary: Un paquete para saludar y despedir
Author-email: Max Salvatierra <hola@max.dev>
License-Expression: MIT
Project-URL: homepage, https://www.maxdev.com
Classifier: Environment :: Console
Classifier: Intended Audience :: End Users/Desktop
Requires-Python: >=3.10
License-File: LICENSE.txt
Dynamic: license-file
